qexo_mcp_server/__init__.py
qexo_mcp_server/__main__.py
qexo_mcp_server/server.py
qexo_mcp-0.1.3.dist-info/METADATA
qexo_mcp-0.1.3.dist-info/WHEEL
qexo_mcp-0.1.3.dist-info/entry_points.txt
qexo_mcp-0.1.3.dist-info/licenses/LICENSE
qexo_mcp-0.1.3.dist-info/RECORD
