Metadata-Version: 2.4
Name: qexo-mcp
Version: 0.1.3
Summary: MCP server implementation for Qexo CMS
Author-email: "yuzhi.jiang" <yefengzhiming@gmail.com>
License: MIT
License-File: LICENSE
Requires-Python: >=3.10
Requires-Dist: httpx
Requires-Dist: mcp[cli]
Requires-Dist: requests>=2.32.3
